LICENSE.txt
MANIFEST.in
README.rst
setup.cfg
setup.py
PyProperties.egg-info/PKG-INFO
PyProperties.egg-info/SOURCES.txt
PyProperties.egg-info/dependency_links.txt
PyProperties.egg-info/top_level.txt
py_properties/PyProperties.py
py_properties/__init__.py
test/test_PyProperties.py
test/resources/test.properties