Metadata-Version: 1.1
Name: PyProperties
Version: 1.0.15
Summary: Python library operating with java properties file
Home-page: https://github.com/seelikes/PyProperties
Author: seelikes
Author-email: seelikes@163.com
License: UNKNOWN
Keywords: py properties
Platform: UNKNOWN
Classifier: Development Status :: 5 - Production/Stable
Classifier: Intended Audience :: Developers
Classifier: Topic :: Software Development :: Build Tools
Classifier: License :: OSI Approved :: MIT License
Classifier: Programming Language :: Python :: 2
Classifier: Programming Language :: Python :: 2.7
Classifier: Programming Language :: Python :: 3
Classifier: Programming Language :: Python :: 3.4
Classifier: Programming Language :: Python :: 3.5
Classifier: Programming Language :: Python :: 3.6
